rabbit_401/__init__.py
rabbit_401-0.0.5.dist-info/LICENSE
rabbit_401-0.0.5.dist-info/METADATA
rabbit_401-0.0.5.dist-info/WHEEL
rabbit_401-0.0.5.dist-info/top_level.txt
rabbit_401-0.0.5.dist-info/RECORD
