Metadata-Version: 2.1
Name: rabbit-401
Version: 0.0.5
Summary: Lightweight In Memory Key Value Database For Python 3+
Home-page: https://github.com/amyyazdan/rabbit-401
Author: Amir Mohammad Yazdani (AmyyazdaN)
Project-URL: Bug Tracker, https://github.com/amyyazdan/rabbit-401/issues
Classifier: Programming Language :: Python :: 3
Classifier: License :: OSI Approved :: Apache Software License
Classifier: Operating System :: OS Independent
Requires-Python: >=3.6
License-File: LICENSE
